layertuber/__init__.py
layertuber/editor/__init__.py
layertuber/editor/window.py
layertuber/rig/__init__.py
layertuber/rig/config.py
layertuber/rig/layer.py
layertuber/rig/rig.py
layertuber/rig/utils.py
layertuber/tracking/__init__.py
layertuber/tracking/face.py
layertuber/tracking/report.py
layertuber/tracking/utils.py
layertuber/utils/cv.py
layertuber/vendor/OpenSeeFace/dshowcapture.py
layertuber/vendor/OpenSeeFace/escapi.py
layertuber/vendor/OpenSeeFace/facetracker.py
layertuber/vendor/OpenSeeFace/input_reader.py
layertuber/vendor/OpenSeeFace/model.py
layertuber/vendor/OpenSeeFace/remedian.py
layertuber/vendor/OpenSeeFace/retinaface.py
layertuber/vendor/OpenSeeFace/similaritytransform.py
layertuber/vendor/OpenSeeFace/tracker.py
layertuber/vendor/OpenSeeFace/models/lm_model0_opt.onnx
layertuber/vendor/OpenSeeFace/models/lm_model1_opt.onnx
layertuber/vendor/OpenSeeFace/models/lm_model2_opt.onnx
layertuber/vendor/OpenSeeFace/models/lm_model3_opt.onnx
layertuber/vendor/OpenSeeFace/models/lm_model4_opt.onnx
layertuber/vendor/OpenSeeFace/models/lm_modelT_opt.onnx
layertuber/vendor/OpenSeeFace/models/lm_modelU_opt.onnx
layertuber/vendor/OpenSeeFace/models/lm_modelV_opt.onnx
layertuber/vendor/OpenSeeFace/models/mnv3_detection_opt.onnx
layertuber/vendor/OpenSeeFace/models/mnv3_gaze32_split_opt.onnx
layertuber/vendor/OpenSeeFace/models/priorbox_640x640.json
layertuber/vendor/OpenSeeFace/models/retinaface_640x640_opt.onnx
layertuber/viewer/__init__.py
layertuber-0.0.3.dist-info/METADATA
layertuber-0.0.3.dist-info/WHEEL
layertuber-0.0.3.dist-info/entry_points.txt
layertuber-0.0.3.dist-info/top_level.txt
layertuber-0.0.3.dist-info/RECORD
